pollyglot/__about__.py
pollyglot/__init__.py
pollyglot/datasets.py
pollyglot/datasets.yaml
pollyglot/fetchfuncs.py
pollyglot/make.py
pollyglot/tarprep.py
pollyglot/urlcopy.py
pollyglot-0.1.1.dist-info/LICENSE-CODE
pollyglot-0.1.1.dist-info/LICENSE-DATA
pollyglot-0.1.1.dist-info/METADATA
pollyglot-0.1.1.dist-info/WHEEL
pollyglot-0.1.1.dist-info/entry_points.txt
pollyglot-0.1.1.dist-info/top_level.txt
pollyglot-0.1.1.dist-info/RECORD
