Metadata-Version: 2.1
Name: pollyglot
Version: 0.1.1
Summary: Small example datasets of annotated vocalizations
Home-page: https://github.com/NickleDave/pollyglot
Author: David Nicholson
Author-email: nicholdav@gmail.com
License: BSD
Platform: UNKNOWN
Classifier: License :: OSI Approved :: BSD License
Classifier: Development Status :: 4 - Beta
Classifier: Programming Language :: Python
Classifier: Programming Language :: Python :: 3
Classifier: Programming Language :: Python :: 3.6
Classifier: Programming Language :: Python :: Implementation :: CPython
Requires-Python: >=3.6.0
Requires-Dist: pyyaml
Requires-Dist: requests
Requires-Dist: tqdm
Requires-Dist: rarfile
